notion_rich_text_analysis/__init__.py
notion_rich_text_analysis/__main__.py
notion_rich_text_analysis/notion_db_text.py
notion_rich_text_analysis/notion_text_analysis.py
notion_rich_text_analysis/parameter/__init__.py
notion_rich_text_analysis/parameter/log.py
notion_rich_text_analysis/parameter/utils.py
notion_rich_text_analysis-1.0.1.dist-info/LICENSE
notion_rich_text_analysis-1.0.1.dist-info/WHEEL
notion_rich_text_analysis-1.0.1.dist-info/METADATA
notion_rich_text_analysis-1.0.1.dist-info/RECORD
