Metadata-Version: 2.1
Name: notion-rich-text-analysis
Version: 1.0.1
Summary: Reading rich text information from a Notion database and performing simple NLP analysis.
License: MIT
Author: dario-github
Author-email: zdclink@gmail.com
Requires-Python: >=3.8.10,<3.9.0
Classifier: License :: OSI Approved :: MIT License
Classifier: Programming Language :: Python :: 3
Provides-Extra: doc
Requires-Dist: arrow (==1.2.3)
Requires-Dist: jieba (==0.42.1)
Requires-Dist: pandas (==1.5.3)
Requires-Dist: pyfunctional (==1.4.3)
Requires-Dist: requests (==2.28.2)
Requires-Dist: ruamel-yaml (==0.17.21)
Requires-Dist: scikit-learn (==1.2.1)
Requires-Dist: tabulate (==0.9.0)
Requires-Dist: tqdm (==4.64.1)
Requires-Dist: typer (==0.7.0)
